{"id":"~01203facb55296a62e","title":"I need a Web scraping","snippet":"Looking for web scrapper who can scrape universities websites to get student emails.","category2":"Web, Mobile & Software Dev","subcategory2":"Other - Software Development","skills":["python","web-scraping"],"job_type":"Fixed","budget":100,"duration":null,"workload":null,"job_status":"Open","date_created":"2016-10-28T17:28:51+0000","url":"http:\/\/www.upwork.com\/jobs\/~01203facb55296a62e","client":{"country":"Pakistan","feedback":0,"reviews_count":0,"jobs_posted":0,"past_hires":0,"payment_verification_status":"UNKNOWN"}}