{"id":"~013c89f0131aac554a","title":"Growth hacker","snippet":"The job requires creativity and analytical thinking to solve problems and move the growth metrics for the project.\r\n\r\nSkills Required\r\n1. Web Crawling\r\n2. Scripting: Javascript\/Ruby\/Python \r\n3. File I\/O: Reading and writing to CSV files. \r\n\r\n\r\nMentorship will be provided if needed. \r\n\r\nFixed pay for the task however I am flexible and can pay hourly once we establish a rapport.","category2":"Web, Mobile & Software Dev","subcategory2":"Scripts & Utilities","skills":["web-crawler","web-scraping"],"job_type":"Fixed","budget":5000,"duration":null,"workload":"30+ hrs\/week","job_status":"Open","date_created":"2016-09-09T22:52:50+0000","url":"http:\/\/www.upwork.com\/jobs\/~013c89f0131aac554a","client":{"country":"United States","feedback":4.1647179766,"reviews_count":42,"jobs_posted":11,"past_hires":82,"payment_verification_status":"VERIFIED"}}