{"id":"~016a703f7ec6528504","title":"Email marketing automation","snippet":"I would like to set up some email automation on my website using Sumome.  I want to offer a lead magnet and collect email addresses into a list.  I also would like to be able to segment lists in the future based on the lead magnet.  I am currently using Mailchimp but I'm not committed and my list is so small it would be easy to move.  In addition to automated my list building, I want to automate some of my social media marketing on Facebook and Twitter.","category2":"Sales & Marketing","subcategory2":"Email & Marketing Automation","skills":[],"job_type":"Hourly","budget":0,"duration":"Less than 1 week","workload":"Less than 10 hrs\/week","job_status":"Open","date_created":"2016-10-29T02:32:44+0000","url":"http:\/\/www.upwork.com\/jobs\/~016a703f7ec6528504","client":{"country":"United States","feedback":5,"reviews_count":4,"jobs_posted":4,"past_hires":4,"payment_verification_status":"VERIFIED"}}