{"id":"~0176b8fc0a717af5f8","title":"Mapping of all Self Storage Facilities in the USA","snippet":"Hello,\nI would like to scrape multiple websites and plot all self storage facilities in the United States along with size and other demographic information.  This information will be used to help determine where there is a need for others to be built.  \n","category2":"Data Science & Analytics","subcategory2":"Other - Data Science & Analytics","skills":[],"job_type":"Fixed","budget":1000,"duration":null,"workload":null,"job_status":"Open","date_created":"2016-10-29T01:46:23+0000","url":"http:\/\/www.upwork.com\/jobs\/~0176b8fc0a717af5f8","client":{"country":"United States","feedback":0,"reviews_count":0,"jobs_posted":25,"past_hires":14,"payment_verification_status":null}}