{"id":"~01d914d6bb3c991ea1","title":"Software Developer","snippet":"Need someone to create and develop a tool that can extract phone numbers from a website then scrub to pull just cell phone numbers and verify them ","category2":"Web, Mobile & Software Dev","subcategory2":"Other - Software Development","skills":[],"job_type":"Hourly","budget":0,"duration":"1 to 3 months","workload":"Less than 10 hrs\/week","job_status":"Open","date_created":"2016-10-27T21:33:35+0000","url":"http:\/\/www.upwork.com\/jobs\/~01d914d6bb3c991ea1","client":{"country":"United States","feedback":4.9379185647,"reviews_count":10,"jobs_posted":74,"past_hires":14,"payment_verification_status":"VERIFIED"}}