{"id":171980377,"id_str":"171980377","name":"Antonio Ortega Masco","screen_name":"Aomascorro","location":"Mexico","description":"","url":null,"entities":{"description":{"urls":[]}},"protected":true,"followers_count":4,"friends_count":1913,"listed_count":0,"created_at":"Wed Jul 28 16:46:39 +0000 2010","favourites_count":1,"utc_offset":-21600,"time_zone":"Mountain Time (US & Canada)","geo_enabled":true,"verified":false,"statuses_count":6,"lang":"es","contributors_enabled":false,"is_translator":false,"is_translation_enabled":false,"profile_background_color":"C0DEED","profile_background_image_url":"http:\/\/pbs.twimg.com\/profile_background_images\/718685224\/bc6b8c8367399575b9fa9e77aacc4fc1.jpeg","profile_background_image_url_https":"https:\/\/pbs.twimg.com\/profile_background_images\/718685224\/bc6b8c8367399575b9fa9e77aacc4fc1.jpeg","profile_background_tile":false,"profile_image_url":"http:\/\/pbs.twimg.com\/profile_images\/2586294945\/0p65ne8fol9kl5j9gdli_normal.jpeg","profile_image_url_https":"https:\/\/pbs.twimg.com\/profile_images\/2586294945\/0p65ne8fol9kl5j9gdli_normal.jpeg","profile_link_color":"0084B4","profile_sidebar_border_color":"FFFFFF","profile_sidebar_fill_color":"DDEEF6","profile_text_color":"333333","profile_use_background_image":true,"has_extended_profile":false,"default_profile":false,"default_profile_image":false,"following":false,"live_following":false,"follow_request_sent":false,"notifications":false,"muting":false,"blocking":false,"blocked_by":false}