{"id":"3728361562","id_str":"3728361562","name":"Candace Williford","screen_name":"coderCandace","location":"Knoxville, TN","description":"I'm an entry level programmer looking for tips and tricks to getting started in the real world as a programmer.","url":"https:\/\/t.co\/dYmoYlPcmu","entities":{"url":{"urls":[{"url":"https:\/\/t.co\/dYmoYlPcmu","expanded_url":"https:\/\/github.com\/Candace-Williford","display_url":"github.com\/Candace-Willif\u2026","indices":[0,23]}]},"description":{"urls":[]}},"protected":false,"followers_count":349,"friends_count":875,"listed_count":2,"created_at":"Mon Sep 21 12:48:52 +0000 2015","favourites_count":27,"utc_offset":null,"time_zone":null,"geo_enabled":false,"verified":false,"statuses_count":49,"lang":"en","status":{"created_at":"Fri Jan 15 14:25:31 +0000 2016","id":"688004086831149058","id_str":"688004086831149058","text":"RT @KozziImages: Deserted desert landscape with cloudy sky by Kozzi #Desert #Sky #Southwest https:\/\/t.co\/MveH70V12b https:\/\/t.co\/Mo8bGiuq88","truncated":false,"entities":{"hashtags":[{"text":"Desert","indices":[68,75]},{"text":"Sky","indices":[76,80]},{"text":"Southwest","indices":[81,91]}],"symbols":[],"user_mentions":[{"screen_name":"KozziImages","name":"Kozzi Images","id":323305899,"id_str":"323305899","indices":[3,15]}],"urls":[{"url":"https:\/\/t.co\/MveH70V12b","expanded_url":"http:\/\/kozzi.tv\/X5fup","display_url":"kozzi.tv\/X5fup","indices":[92,115]}],"media":[{"id":"687986449237557248","id_str":"687986449237557248","indices":[116,139],"media_url":"http:\/\/pbs.twimg.com\/media\/CYw4B80WQAAHdz8.jpg","media_url_https":"https:\/\/pbs.twimg.com\/media\/CYw4B80WQAAHdz8.jpg","url":"https:\/\/t.co\/Mo8bGiuq88","display_url":"pic.twitter.com\/Mo8bGiuq88","expanded_url":"http:\/\/twitter.com\/KozziImages\/status\/687986449770278912\/photo\/1","type":"photo","sizes":{"large":{"w":1024,"h":768,"resize":"fit"},"thumb":{"w":150,"h":150,"resize":"crop"},"medium":{"w":600,"h":450,"resize":"fit"},"small":{"w":340,"h":255,"resize":"fit"}},"source_status_id":"687986449770278912","source_status_id_str":"687986449770278912","source_user_id":323305899,"source_user_id_str":"323305899"}]},"extended_entities":{"media":[{"id":"687986449237557248","id_str":"687986449237557248","indices":[116,139],"media_url":"http:\/\/pbs.twimg.com\/media\/CYw4B80WQAAHdz8.jpg","media_url_https":"https:\/\/pbs.twimg.com\/media\/CYw4B80WQAAHdz8.jpg","url":"https:\/\/t.co\/Mo8bGiuq88","display_url":"pic.twitter.com\/Mo8bGiuq88","expanded_url":"http:\/\/twitter.com\/KozziImages\/status\/687986449770278912\/photo\/1","type":"photo","sizes":{"large":{"w":1024,"h":768,"resize":"fit"},"thumb":{"w":150,"h":150,"resize":"crop"},"medium":{"w":600,"h":450,"resize":"fit"},"small":{"w":340,"h":255,"resize":"fit"}},"source_status_id":"687986449770278912","source_status_id_str":"687986449770278912","source_user_id":323305899,"source_user_id_str":"323305899"}]},"source":"<a href=\"http:\/\/twitter.com\" rel=\"nofollow\">Twitter Web Client<\/a>","in_reply_to_status_id":null,"in_reply_to_status_id_str":null,"in_reply_to_user_id":null,"in_reply_to_user_id_str":null,"in_reply_to_screen_name":null,"geo":null,"coordinates":null,"place":null,"contributors":null,"retweeted_status":{"created_at":"Fri Jan 15 13:15:26 +0000 2016","id":"687986449770278912","id_str":"687986449770278912","text":"Deserted desert landscape with cloudy sky by Kozzi #Desert #Sky #Southwest https:\/\/t.co\/MveH70V12b https:\/\/t.co\/Mo8bGiuq88","truncated":false,"entities":{"hashtags":[{"text":"Desert","indices":[51,58]},{"text":"Sky","indices":[59,63]},{"text":"Southwest","indices":[64,74]}],"symbols":[],"user_mentions":[],"urls":[{"url":"https:\/\/t.co\/MveH70V12b","expanded_url":"http:\/\/kozzi.tv\/X5fup","display_url":"kozzi.tv\/X5fup","indices":[75,98]}],"media":[{"id":"687986449237557248","id_str":"687986449237557248","indices":[99,122],"media_url":"http:\/\/pbs.twimg.com\/media\/CYw4B80WQAAHdz8.jpg","media_url_https":"https:\/\/pbs.twimg.com\/media\/CYw4B80WQAAHdz8.jpg","url":"https:\/\/t.co\/Mo8bGiuq88","display_url":"pic.twitter.com\/Mo8bGiuq88","expanded_url":"http:\/\/twitter.com\/KozziImages\/status\/687986449770278912\/photo\/1","type":"photo","sizes":{"large":{"w":1024,"h":768,"resize":"fit"},"thumb":{"w":150,"h":150,"resize":"crop"},"medium":{"w":600,"h":450,"resize":"fit"},"small":{"w":340,"h":255,"resize":"fit"}}}]},"extended_entities":{"media":[{"id":"687986449237557248","id_str":"687986449237557248","indices":[99,122],"media_url":"http:\/\/pbs.twimg.com\/media\/CYw4B80WQAAHdz8.jpg","media_url_https":"https:\/\/pbs.twimg.com\/media\/CYw4B80WQAAHdz8.jpg","url":"https:\/\/t.co\/Mo8bGiuq88","display_url":"pic.twitter.com\/Mo8bGiuq88","expanded_url":"http:\/\/twitter.com\/KozziImages\/status\/687986449770278912\/photo\/1","type":"photo","sizes":{"large":{"w":1024,"h":768,"resize":"fit"},"thumb":{"w":150,"h":150,"resize":"crop"},"medium":{"w":600,"h":450,"resize":"fit"},"small":{"w":340,"h":255,"resize":"fit"}}}]},"source":"<a href=\"http:\/\/www.hootsuite.com\" rel=\"nofollow\">Hootsuite<\/a>","in_reply_to_status_id":null,"in_reply_to_status_id_str":null,"in_reply_to_user_id":null,"in_reply_to_user_id_str":null,"in_reply_to_screen_name":null,"geo":null,"coordinates":null,"place":null,"contributors":null,"is_quote_status":false,"retweet_count":8,"favorite_count":77,"favorited":false,"retweeted":false,"possibly_sensitive":false,"lang":"en"},"is_quote_status":false,"retweet_count":8,"favorite_count":0,"favorited":false,"retweeted":false,"possibly_sensitive":false,"lang":"en"},"contributors_enabled":false,"is_translator":false,"is_translation_enabled":false,"profile_background_color":"642D8B","profile_background_image_url":"http:\/\/abs.twimg.com\/images\/themes\/theme10\/bg.gif","profile_background_image_url_https":"https:\/\/abs.twimg.com\/images\/themes\/theme10\/bg.gif","profile_background_tile":true,"profile_image_url":"http:\/\/pbs.twimg.com\/profile_images\/645949931891609600\/XauoVlbq_normal.jpg","profile_image_url_https":"https:\/\/pbs.twimg.com\/profile_images\/645949931891609600\/XauoVlbq_normal.jpg","profile_link_color":"9266CC","profile_sidebar_border_color":"000000","profile_sidebar_fill_color":"000000","profile_text_color":"000000","profile_use_background_image":true,"has_extended_profile":false,"default_profile":false,"default_profile_image":false,"following":false,"live_following":false,"follow_request_sent":false,"notifications":false,"muting":false,"blocking":false,"blocked_by":false}