{"id":400143160,"id_str":"400143160","name":"Jacob","screen_name":"cyberjacob","location":"","description":"Wake up!  Life is happening.","url":null,"entities":{"description":{"urls":[]}},"protected":false,"followers_count":70,"friends_count":140,"listed_count":1,"created_at":"Fri Oct 28 15:27:57 +0000 2011","favourites_count":33,"utc_offset":null,"time_zone":null,"geo_enabled":false,"verified":false,"statuses_count":2238,"lang":"en","status":{"created_at":"Thu Sep 29 20:48:41 +0000 2016","id":"781596583469002753","id_str":"781596583469002753","text":"@HillaryClinton Actually, I kinda have to sit this one out. I'm one of the 400lb hackers laying in my bed Trump referred to #400lbhacker. :(","truncated":false,"entities":{"hashtags":[{"text":"400lbhacker","indices":[124,136]}],"symbols":[],"user_mentions":[{"screen_name":"HillaryClinton","name":"Hillary Clinton","id":1339835893,"id_str":"1339835893","indices":[0,15]}],"urls":[]},"source":"<a href=\"http:\/\/twitter.com\" rel=\"nofollow\">Twitter Web Client<\/a>","in_reply_to_status_id":"780448183356891136","in_reply_to_status_id_str":"780448183356891136","in_reply_to_user_id":1339835893,"in_reply_to_user_id_str":"1339835893","in_reply_to_screen_name":"HillaryClinton","geo":null,"coordinates":null,"place":null,"contributors":null,"is_quote_status":false,"retweet_count":0,"favorite_count":0,"favorited":false,"retweeted":false,"lang":"en"},"contributors_enabled":false,"is_translator":false,"is_translation_enabled":false,"profile_background_color":"131516","profile_background_image_url":"http:\/\/pbs.twimg.com\/profile_background_images\/631616099323277313\/HTe4MpY4.jpg","profile_background_image_url_https":"https:\/\/pbs.twimg.com\/profile_background_images\/631616099323277313\/HTe4MpY4.jpg","profile_background_tile":true,"profile_image_url":"http:\/\/pbs.twimg.com\/profile_images\/1615178585\/photo_3__normal.jpg","profile_image_url_https":"https:\/\/pbs.twimg.com\/profile_images\/1615178585\/photo_3__normal.jpg","profile_link_color":"009999","profile_sidebar_border_color":"000000","profile_sidebar_fill_color":"000000","profile_text_color":"000000","profile_use_background_image":true,"has_extended_profile":false,"default_profile":false,"default_profile_image":false,"following":false,"live_following":false,"follow_request_sent":false,"notifications":false,"muting":false,"blocking":false,"blocked_by":false}