{"id":"2687006514","id_str":"2687006514","name":"Game of Hacks","screen_name":"GameofHacks","location":"","description":"Which vulnerability am I? #AppSec game for all levels - compete against others or play on your own and test your security skillz!","url":"http:\/\/t.co\/cETZr1YNfZ","entities":{"url":{"urls":[{"url":"http:\/\/t.co\/cETZr1YNfZ","expanded_url":"http:\/\/gameofhacks.com","display_url":"gameofhacks.com","indices":[0,22]}]},"description":{"urls":[]}},"protected":false,"followers_count":451,"friends_count":165,"listed_count":46,"created_at":"Mon Jul 28 08:38:50 +0000 2014","favourites_count":185,"utc_offset":null,"time_zone":null,"geo_enabled":false,"verified":false,"statuses_count":2116,"lang":"en","status":{"created_at":"Mon Oct 03 12:29:08 +0000 2016","id":"782920419414343681","id_str":"782920419414343681","text":"Come say hi to Checkmarx at #CELAES2016! We're at booth 13! \n@FIBA_BANKERS https:\/\/t.co\/GRUqtJGiMZ","truncated":false,"entities":{"hashtags":[{"text":"CELAES2016","indices":[28,39]}],"symbols":[],"user_mentions":[{"screen_name":"FIBA_BANKERS","name":"FIBA Bankers","id":218530550,"id_str":"218530550","indices":[61,74]}],"urls":[],"media":[{"id":"782920416486621184","id_str":"782920416486621184","indices":[75,98],"media_url":"http:\/\/pbs.twimg.com\/media\/Ct19-IAWAAAgUch.png","media_url_https":"https:\/\/pbs.twimg.com\/media\/Ct19-IAWAAAgUch.png","url":"https:\/\/t.co\/GRUqtJGiMZ","display_url":"pic.twitter.com\/GRUqtJGiMZ","expanded_url":"https:\/\/twitter.com\/GameofHacks\/status\/782920419414343681\/photo\/1","type":"photo","sizes":{"large":{"w":1200,"h":627,"resize":"fit"},"medium":{"w":1200,"h":627,"resize":"fit"},"thumb":{"w":150,"h":150,"resize":"crop"},"small":{"w":680,"h":355,"resize":"fit"}}}]},"extended_entities":{"media":[{"id":"782920416486621184","id_str":"782920416486621184","indices":[75,98],"media_url":"http:\/\/pbs.twimg.com\/media\/Ct19-IAWAAAgUch.png","media_url_https":"https:\/\/pbs.twimg.com\/media\/Ct19-IAWAAAgUch.png","url":"https:\/\/t.co\/GRUqtJGiMZ","display_url":"pic.twitter.com\/GRUqtJGiMZ","expanded_url":"https:\/\/twitter.com\/GameofHacks\/status\/782920419414343681\/photo\/1","type":"photo","sizes":{"large":{"w":1200,"h":627,"resize":"fit"},"medium":{"w":1200,"h":627,"resize":"fit"},"thumb":{"w":150,"h":150,"resize":"crop"},"small":{"w":680,"h":355,"resize":"fit"}}}]},"source":"<a href=\"http:\/\/bufferapp.com\" rel=\"nofollow\">Buffer<\/a>","in_reply_to_status_id":null,"in_reply_to_status_id_str":null,"in_reply_to_user_id":null,"in_reply_to_user_id_str":null,"in_reply_to_screen_name":null,"geo":null,"coordinates":null,"place":null,"contributors":null,"is_quote_status":false,"retweet_count":0,"favorite_count":0,"favorited":false,"retweeted":false,"possibly_sensitive":false,"lang":"en"},"contributors_enabled":false,"is_translator":false,"is_translation_enabled":false,"profile_background_color":"000000","profile_background_image_url":"http:\/\/abs.twimg.com\/images\/themes\/theme1\/bg.png","profile_background_image_url_https":"https:\/\/abs.twimg.com\/images\/themes\/theme1\/bg.png","profile_background_tile":false,"profile_image_url":"http:\/\/pbs.twimg.com\/profile_images\/493677994854985729\/qc7EkbCp_normal.png","profile_image_url_https":"https:\/\/pbs.twimg.com\/profile_images\/493677994854985729\/qc7EkbCp_normal.png","profile_banner_url":"https:\/\/pbs.twimg.com\/profile_banners\/2687006514\/1407047899","profile_link_color":"2BB8BD","profile_sidebar_border_color":"000000","profile_sidebar_fill_color":"000000","profile_text_color":"000000","profile_use_background_image":false,"has_extended_profile":false,"default_profile":false,"default_profile_image":false,"following":false,"live_following":false,"follow_request_sent":false,"notifications":false,"muting":false,"blocking":false,"blocked_by":false}