{"id":1082484476,"id_str":"1082484476","name":"Pratik Singh","screen_name":"Pratik_Singh99","location":"India","description":"I love those people who like one Direction nd Eminem (; nd Westlife also.. (;","url":null,"entities":{"description":{"urls":[]}},"protected":false,"followers_count":377,"friends_count":1450,"listed_count":1,"created_at":"Sat Jan 12 10:06:23 +0000 2013","favourites_count":865,"utc_offset":null,"time_zone":null,"geo_enabled":true,"verified":false,"statuses_count":104,"lang":"en","status":{"created_at":"Sun Mar 15 02:19:00 +0000 2015","id":"576930566936797184","id_str":"576930566936797184","text":"\"@vickyvivek981: @asliyoyo \ud83c\udf82Happy birthday YO YO\ud83c\udf82 http:\/\/t.co\/UXbp9lVO38\"Happy birthday Y.Y.H.S","truncated":false,"entities":{"hashtags":[],"symbols":[],"user_mentions":[{"screen_name":"vickyvivek981","name":"Vivek Kashyap","id":1171868934,"id_str":"1171868934","indices":[1,15]},{"screen_name":"asliyoyo","name":"Yo Yo Honey Singh","id":769727912,"id_str":"769727912","indices":[17,26]}],"urls":[],"media":[{"id":"576847363014184960","id_str":"576847363014184960","indices":[50,72],"media_url":"http:\/\/pbs.twimg.com\/media\/CAFfntIU0AARPAz.jpg","media_url_https":"https:\/\/pbs.twimg.com\/media\/CAFfntIU0AARPAz.jpg","url":"http:\/\/t.co\/UXbp9lVO38","display_url":"pic.twitter.com\/UXbp9lVO38","expanded_url":"http:\/\/twitter.com\/vickyvivek981\/status\/576847522519351296\/photo\/1","type":"photo","sizes":{"medium":{"w":600,"h":800,"resize":"fit"},"small":{"w":340,"h":453,"resize":"fit"},"thumb":{"w":150,"h":150,"resize":"crop"},"large":{"w":720,"h":960,"resize":"fit"}},"source_status_id":"576847522519351296","source_status_id_str":"576847522519351296","source_user_id":1171868934,"source_user_id_str":"1171868934"}]},"extended_entities":{"media":[{"id":"576847363014184960","id_str":"576847363014184960","indices":[50,72],"media_url":"http:\/\/pbs.twimg.com\/media\/CAFfntIU0AARPAz.jpg","media_url_https":"https:\/\/pbs.twimg.com\/media\/CAFfntIU0AARPAz.jpg","url":"http:\/\/t.co\/UXbp9lVO38","display_url":"pic.twitter.com\/UXbp9lVO38","expanded_url":"http:\/\/twitter.com\/vickyvivek981\/status\/576847522519351296\/photo\/1","type":"photo","sizes":{"medium":{"w":600,"h":800,"resize":"fit"},"small":{"w":340,"h":453,"resize":"fit"},"thumb":{"w":150,"h":150,"resize":"crop"},"large":{"w":720,"h":960,"resize":"fit"}},"source_status_id":"576847522519351296","source_status_id_str":"576847522519351296","source_user_id":1171868934,"source_user_id_str":"1171868934"}]},"source":"<a href=\"http:\/\/twitter.com\/download\/android\" rel=\"nofollow\">Twitter for Android<\/a>","in_reply_to_status_id":null,"in_reply_to_status_id_str":null,"in_reply_to_user_id":null,"in_reply_to_user_id_str":null,"in_reply_to_screen_name":null,"geo":null,"coordinates":null,"place":null,"contributors":null,"is_quote_status":false,"retweet_count":0,"favorite_count":28,"favorited":false,"retweeted":false,"possibly_sensitive":false,"lang":"en"},"contributors_enabled":false,"is_translator":false,"is_translation_enabled":false,"profile_background_color":"C0DEED","profile_background_image_url":"http:\/\/abs.twimg.com\/images\/themes\/theme1\/bg.png","profile_background_image_url_https":"https:\/\/abs.twimg.com\/images\/themes\/theme1\/bg.png","profile_background_tile":false,"profile_image_url":"http:\/\/pbs.twimg.com\/profile_images\/500628743849668610\/lACF4iXj_normal.jpeg","profile_image_url_https":"https:\/\/pbs.twimg.com\/profile_images\/500628743849668610\/lACF4iXj_normal.jpeg","profile_banner_url":"https:\/\/pbs.twimg.com\/profile_banners\/1082484476\/1400350061","profile_link_color":"0084B4","profile_sidebar_border_color":"C0DEED","profile_sidebar_fill_color":"DDEEF6","profile_text_color":"333333","profile_use_background_image":true,"has_extended_profile":false,"default_profile":true,"default_profile_image":false,"following":false,"live_following":false,"follow_request_sent":false,"notifications":false,"muting":false,"blocking":false,"blocked_by":false}