{"id":1972907592,"id_str":"1972907592","name":"Privacy4Privasee","screen_name":"S_Clarke22","location":"UK","description":"Doing Privacy for @Privasee: Practical #GDPR & #DataProtection solutions. Too much 'Why' and too little 'How'. That's what we're here for :-)","url":"https:\/\/t.co\/LzcpcZy6fI","entities":{"url":{"urls":[{"url":"https:\/\/t.co\/LzcpcZy6fI","expanded_url":"http:\/\/www.privasee.eu","display_url":"privasee.eu","indices":[0,23]}]},"description":{"urls":[]}},"protected":false,"followers_count":3164,"friends_count":1825,"listed_count":387,"created_at":"Sat Oct 19 21:52:33 +0000 2013","favourites_count":14899,"utc_offset":3600,"time_zone":"Europe\/London","geo_enabled":false,"verified":false,"statuses_count":24631,"lang":"en","status":{"created_at":"Mon Oct 03 09:21:54 +0000 2016","id":"782873300636532736","id_str":"782873300636532736","text":"@S_Clarke22 Apropos of nothing except the surprise when I saw it :-)","truncated":false,"entities":{"hashtags":[],"symbols":[],"user_mentions":[{"screen_name":"S_Clarke22","name":"Privacy4Privasee","id":1972907592,"id_str":"1972907592","indices":[0,11]}],"urls":[]},"source":"<a href=\"http:\/\/twitter.com\/download\/android\" rel=\"nofollow\">Twitter for Android<\/a>","in_reply_to_status_id":"782873104750092288","in_reply_to_status_id_str":"782873104750092288","in_reply_to_user_id":1972907592,"in_reply_to_user_id_str":"1972907592","in_reply_to_screen_name":"S_Clarke22","geo":null,"coordinates":null,"place":null,"contributors":null,"is_quote_status":false,"retweet_count":0,"favorite_count":0,"favorited":false,"retweeted":false,"lang":"en"},"contributors_enabled":false,"is_translator":false,"is_translation_enabled":false,"profile_background_color":"131516","profile_background_image_url":"http:\/\/pbs.twimg.com\/profile_background_images\/517599716809269248\/a4z5ck-P.jpeg","profile_background_image_url_https":"https:\/\/pbs.twimg.com\/profile_background_images\/517599716809269248\/a4z5ck-P.jpeg","profile_background_tile":false,"profile_image_url":"http:\/\/pbs.twimg.com\/profile_images\/591399867655794688\/5UU36G7z_normal.jpg","profile_image_url_https":"https:\/\/pbs.twimg.com\/profile_images\/591399867655794688\/5UU36G7z_normal.jpg","profile_banner_url":"https:\/\/pbs.twimg.com\/profile_banners\/1972907592\/1466446395","profile_link_color":"2E64FE","profile_sidebar_border_color":"000000","profile_sidebar_fill_color":"EFEFEF","profile_text_color":"333333","profile_use_background_image":true,"has_extended_profile":false,"default_profile":false,"default_profile_image":false,"following":false,"live_following":false,"follow_request_sent":false,"notifications":false,"muting":false,"blocking":false,"blocked_by":false}