{"id":"3186251930","id_str":"3186251930","name":"SectiveNet","screen_name":"SectiveNet","location":"","description":"Share, Discuss and Explore Information security on http:\/\/t.co\/NcfEIDynDh. Join us, Be a part of #Infosec","url":"http:\/\/t.co\/g69WlnX5jb","entities":{"url":{"urls":[{"url":"http:\/\/t.co\/g69WlnX5jb","expanded_url":"http:\/\/www.sectivenet.com","display_url":"sectivenet.com","indices":[0,22]}]},"description":{"urls":[{"url":"http:\/\/t.co\/NcfEIDynDh","expanded_url":"http:\/\/SectiveNet.com","display_url":"SectiveNet.com","indices":[51,73]}]}},"protected":false,"followers_count":95,"friends_count":314,"listed_count":70,"created_at":"Tue May 05 13:51:48 +0000 2015","favourites_count":14,"utc_offset":-25200,"time_zone":"Pacific Time (US & Canada)","geo_enabled":false,"verified":false,"statuses_count":852,"lang":"en","status":{"created_at":"Thu Aug 25 13:17:28 +0000 2016","id":"768799453797093376","id_str":"768799453797093376","text":"Webinar: Protect against #ransomware with a next-gen intrusion prevention system #IBMXGS https:\/\/t.co\/S1b02qF5Yo","truncated":false,"entities":{"hashtags":[{"text":"ransomware","indices":[25,36]},{"text":"IBMXGS","indices":[81,88]}],"symbols":[],"user_mentions":[],"urls":[{"url":"https:\/\/t.co\/S1b02qF5Yo","expanded_url":"http:\/\/shrd.vu\/bjUcq","display_url":"shrd.vu\/bjUcq","indices":[89,112]}]},"source":"<a href=\"http:\/\/sharedvue.com\/\" rel=\"nofollow\">SharedVue Platform<\/a>","in_reply_to_status_id":null,"in_reply_to_status_id_str":null,"in_reply_to_user_id":null,"in_reply_to_user_id_str":null,"in_reply_to_screen_name":null,"geo":null,"coordinates":null,"place":null,"contributors":null,"is_quote_status":false,"retweet_count":0,"favorite_count":0,"favorited":false,"retweeted":false,"possibly_sensitive":false,"lang":"en"},"contributors_enabled":false,"is_translator":false,"is_translation_enabled":false,"profile_background_color":"000000","profile_background_image_url":"http:\/\/abs.twimg.com\/images\/themes\/theme1\/bg.png","profile_background_image_url_https":"https:\/\/abs.twimg.com\/images\/themes\/theme1\/bg.png","profile_background_tile":false,"profile_image_url":"http:\/\/pbs.twimg.com\/profile_images\/595587499864432642\/G_DbM2Cs_normal.png","profile_image_url_https":"https:\/\/pbs.twimg.com\/profile_images\/595587499864432642\/G_DbM2Cs_normal.png","profile_banner_url":"https:\/\/pbs.twimg.com\/profile_banners\/3186251930\/1430835382","profile_link_color":"4A913C","profile_sidebar_border_color":"000000","profile_sidebar_fill_color":"000000","profile_text_color":"000000","profile_use_background_image":false,"has_extended_profile":false,"default_profile":false,"default_profile_image":false,"following":false,"live_following":false,"follow_request_sent":false,"notifications":false,"muting":false,"blocking":false,"blocked_by":false}