{"id":116092204,"id_str":"116092204","name":"sidiclei luiz zamin","screen_name":"sidiclei_13","location":"brasil","description":"eu sou o que sou","url":null,"entities":{"description":{"urls":[]}},"protected":false,"followers_count":13,"friends_count":1793,"listed_count":0,"created_at":"Sun Feb 21 04:08:28 +0000 2010","favourites_count":0,"utc_offset":-21600,"time_zone":"Chihuahua","geo_enabled":false,"verified":false,"statuses_count":118,"lang":"en","status":{"created_at":"Wed Mar 26 19:41:48 +0000 2014","id":"448907689218039808","id_str":"448907689218039808","text":"\u043a\u0430\u043a \u0432\u044b\u043b\u0435\u0447\u0438\u0442\u044c \u043d\u0430 \u043d\u043e\u0433\u0430\u0445 \u0432\u0430\u0440\u0438\u043a\u043e\u0437 http:\/\/t.co\/naFIfUpoFF","truncated":false,"entities":{"hashtags":[],"symbols":[],"user_mentions":[],"urls":[{"url":"http:\/\/t.co\/naFIfUpoFF","expanded_url":"http:\/\/e-sta.ru\/ihthxfahg\/b-28165.html","display_url":"e-sta.ru\/ihthxfahg\/b-28\u2026","indices":[30,52]}]},"source":"<a href=\"http:\/\/twitter.com\" rel=\"nofollow\">Twitter Web Client<\/a>","in_reply_to_status_id":null,"in_reply_to_status_id_str":null,"in_reply_to_user_id":null,"in_reply_to_user_id_str":null,"in_reply_to_screen_name":null,"geo":null,"coordinates":null,"place":null,"contributors":null,"is_quote_status":false,"retweet_count":0,"favorite_count":4,"favorited":false,"retweeted":false,"possibly_sensitive":false,"lang":"ru"},"contributors_enabled":false,"is_translator":false,"is_translation_enabled":false,"profile_background_color":"0099B9","profile_background_image_url":"http:\/\/pbs.twimg.com\/profile_background_images\/80517904\/PICT0019.JPG","profile_background_image_url_https":"https:\/\/pbs.twimg.com\/profile_background_images\/80517904\/PICT0019.JPG","profile_background_tile":true,"profile_image_url":"http:\/\/pbs.twimg.com\/profile_images\/1776641110\/images_normal.jpg","profile_image_url_https":"https:\/\/pbs.twimg.com\/profile_images\/1776641110\/images_normal.jpg","profile_link_color":"0099B9","profile_sidebar_border_color":"5ED4DC","profile_sidebar_fill_color":"95E8EC","profile_text_color":"3C3940","profile_use_background_image":true,"has_extended_profile":false,"default_profile":false,"default_profile_image":false,"following":false,"live_following":false,"follow_request_sent":false,"notifications":false,"muting":false,"blocking":false,"blocked_by":false}